ansys/aedt/toolkits/magnet_segmentation/__init__.py
ansys/aedt/toolkits/magnet_segmentation/run_toolkit.py
ansys/aedt/toolkits/magnet_segmentation/backend/__init__.py
ansys/aedt/toolkits/magnet_segmentation/backend/aedt_properties.toml
ansys/aedt/toolkits/magnet_segmentation/backend/api.py
ansys/aedt/toolkits/magnet_segmentation/backend/models.py
ansys/aedt/toolkits/magnet_segmentation/backend/run_backend.py
ansys/aedt/toolkits/magnet_segmentation/backend/workflows/__init__.py
ansys/aedt/toolkits/magnet_segmentation/backend/workflows/aedt.py
ansys/aedt/toolkits/magnet_segmentation/ui/__init__.py
ansys/aedt/toolkits/magnet_segmentation/ui/actions.py
ansys/aedt/toolkits/magnet_segmentation/ui/frontend_properties.toml
ansys/aedt/toolkits/magnet_segmentation/ui/models.py
ansys/aedt/toolkits/magnet_segmentation/ui/run_frontend.py
ansys/aedt/toolkits/magnet_segmentation/ui/splash.png
ansys/aedt/toolkits/magnet_segmentation/ui/splash.py
ansys/aedt/toolkits/magnet_segmentation/ui/windows/help/__init__.py
ansys/aedt/toolkits/magnet_segmentation/ui/windows/help/help_column.py
ansys/aedt/toolkits/magnet_segmentation/ui/windows/help/help_column.ui
ansys/aedt/toolkits/magnet_segmentation/ui/windows/help/help_menu.py
ansys/aedt/toolkits/magnet_segmentation/ui/windows/help/help_page.py
ansys/aedt/toolkits/magnet_segmentation/ui/windows/help/help_page.ui
ansys/aedt/toolkits/magnet_segmentation/ui/windows/plot_design/__init__.py
ansys/aedt/toolkits/magnet_segmentation/ui/windows/plot_design/plot_design_column.py
ansys/aedt/toolkits/magnet_segmentation/ui/windows/plot_design/plot_design_column.ui
ansys/aedt/toolkits/magnet_segmentation/ui/windows/plot_design/plot_design_menu.py
ansys/aedt/toolkits/magnet_segmentation/ui/windows/plot_design/plot_design_page.py
ansys/aedt/toolkits/magnet_segmentation/ui/windows/plot_design/plot_design_page.ui
ansys/aedt/toolkits/magnet_segmentation/ui/windows/post_processing/post_processing_column.py
ansys_magnet_segmentation_toolkit-0.8.5.dist-info/LICENSE
ansys_magnet_segmentation_toolkit-0.8.5.dist-info/WHEEL
ansys_magnet_segmentation_toolkit-0.8.5.dist-info/METADATA
ansys_magnet_segmentation_toolkit-0.8.5.dist-info/RECORD
