Metadata-Version: 2.3
Name: ansys-magnet-segmentation-toolkit
Version: 0.8.5
Summary: Toolkit used for automating the segmentation and skew of interior permanent magnet (IPM) and surface permanent magnet (SPM) motors using Ansys Electronics Desktop (AEDT)
Author-email: "ANSYS, Inc." <pyansys.support@ansys.com>
Maintainer-email: PyAnsys developers <pyansys.maintainers@ansys.com>
Requires-Python: >=3.10
Classifier: Development Status :: 4 - Beta
Classifier: Programming Language :: Python :: 3
Classifier: License :: OSI Approved :: MIT License
Classifier: Operating System :: OS Independent
Requires-Dist: ansys-aedt-toolkits-common[all]
Requires-Dist: ansys-aedt-toolkits-common[all] ; extra == "all"
Requires-Dist: ansys-aedt-toolkits-common[doc] ; extra == "doc"
Requires-Dist: pyinstaller ; extra == "freeze"
Requires-Dist: ansys-aedt-toolkits-common[tests] ; extra == "tests"
Project-URL: Changelog, https://github.com/ansys/magnet-segmentation-toolkit/blob/main/doc/source/changelog.rst
Project-URL: Documentation, https://magnet.segmentation.toolkit.docs.pyansys.com/
Project-URL: Issues, https://github.com/ansys/magnet-segmentation-toolkit.git/issues
Project-URL: Releases, https://github.com/ansys/magnet-segmentation-toolkit/releases
Project-URL: Source, https://github.com/ansys/magnet-segmentation-toolkit.git
Provides-Extra: all
Provides-Extra: doc
Provides-Extra: freeze
Provides-Extra: tests
